MANIFEST.in
README.md
setup.py
bin/komics
komics/__init__.py
komics/assemble.py
komics/bam2fq.py
komics/circularize.py
komics/polish.py
komics/qualcheck.py
komics/trimfq.py
komics/commands/__init__.py
komics/commands/all.py
komics/commands/all2.py
komics/commands/assemble.py
komics/commands/bam2fq.py
komics/commands/circularize.py
komics/commands/polish.py
komics/commands/qualcheck.py
komics/commands/trimfq.py