Metadata-Version: 1.1
Name: komics
Version: 1.1.8
Summary: Kinetoplast genOMICS
Home-page: http://github.com/frebio/komics
Author: Frederik Van den Broeck
Author-email: fvandenbroeck@itg.be
License: GPLv3
Keywords: megahit blast circular assembly circularization
Platform: UNKNOWN
Classifier: Development Status :: 2 - Pre-Alpha
Classifier: Topic :: Scientific/Engineering :: Bio-Informatics
Classifier: Programming Language :: Python :: 3.7
Classifier: License :: OSI Approved :: GNU General Public License v3 (GPLv3)
